obpages/__init__.py
obpages/_version.py
obpages/admin.py
obpages/apps.py
obpages/fields.py
obpages/forms.py
obpages/indexes.py
obpages/models.py
obpages/paginator.py
obpages/serialize.py
obpages/tasks.py
obpages/urls.py
obpages/utils.py
obpages/views.py
obpages/accounts/__init__.py
obpages/accounts/forms.py
obpages/accounts/tasks.py
obpages/accounts/urls.py
obpages/accounts/views.py
obpages/migrations/0001_initial.py
obpages/migrations/0002_feedbacknote.py
obpages/migrations/0003_usersequence_create_timestamp_and_more.py
obpages/migrations/0004_usersequence_curated.py
obpages/migrations/0005_alter_usersequence_options.py
obpages/migrations/0006_curatedcontentitem.py
obpages/migrations/0007_feedbacknote_spam_score.py
obpages/migrations/0008_update_searchindex.py
obpages/migrations/__init__.py
obpages/static/obpages/social-link-image.svg
obpages/static/obpages/css/base.css
obpages/static/obpages/css/reset.css
obpages/static/obpages/favicons/favicon-16x16.png
obpages/static/obpages/favicons/favicon-180x180.png
obpages/static/obpages/favicons/favicon-32x32.png
obpages/static/obpages/favicons/favicon-57x57.png
obpages/static/obpages/favicons/favicon.svg
obpages/static/obpages/fonts/merriweather.woff2
obpages/static/obpages/icons/essaycontentitem.svg
obpages/static/obpages/icons/external-link.svg
obpages/static/obpages/icons/obcontentitem.svg
obpages/static/obpages/icons/spotifycontentitem.svg
obpages/static/obpages/icons/youtubecontentitem.svg
obpages/templates/404.html
obpages/templates/500.html
obpages/templates/admin/base_site.html
obpages/templates/django/forms/default.html
obpages/templates/obpages/about.html
obpages/templates/obpages/base.html
obpages/templates/obpages/content_detail.html
obpages/templates/obpages/explore_base.html
obpages/templates/obpages/explore_detail.html
obpages/templates/obpages/explore_list.html
obpages/templates/obpages/feedback.html
obpages/templates/obpages/feedback_done.html
obpages/templates/obpages/home.html
django_overcomingbias_pages-0.7.4.dist-info/METADATA
django_overcomingbias_pages-0.7.4.dist-info/WHEEL
django_overcomingbias_pages-0.7.4.dist-info/licenses/LICENSE
django_overcomingbias_pages-0.7.4.dist-info/RECORD
