Metadata-Version: 2.1
Name: django-overcomingbias-pages
Version: 0.7.4
Summary: django app web interface to Robin Hanson's content
Project-URL: repository, https://github.com/chris-mcdo/django-overcomingbias-pages
Project-URL: issues, https://github.com/chris-mcdo/django-overcomingbias-pages/issues
Author-email: Christopher McDonald <cmcdonal33@gmail.com>
License: MIT License
License-File: LICENSE
Keywords: content,django,overcomingbias,scrape,website
Classifier: Development Status :: 4 - Beta
Classifier: Environment :: Web Environment
Classifier: Framework :: Django
Classifier: Intended Audience :: Developers
Classifier: License :: OSI Approved :: MIT License
Classifier: Operating System :: MacOS :: MacOS X
Classifier: Operating System :: Microsoft :: Windows
Classifier: Operating System :: POSIX
Classifier: Programming Language :: Python :: 3
Classifier: Programming Language :: Python :: 3 :: Only
Classifier: Programming Language :: Python :: 3.8
Classifier: Programming Language :: Python :: 3.9
Classifier: Programming Language :: Python :: 3.10
Classifier: Topic :: Internet
Classifier: Topic :: Internet :: WWW/HTTP
Classifier: Topic :: Internet :: WWW/HTTP :: Dynamic Content
Classifier: Topic :: Internet :: WWW/HTTP :: Indexing/Search
Requires-Python: >=3.8
Requires-Dist: django-overcomingbias-api
Requires-Dist: django-select2
Requires-Dist: django<5,>=4.0
Requires-Dist: huey>=2
Requires-Dist: meilisearch
Requires-Dist: python-slugify>=5
Provides-Extra: production
Requires-Dist: django-overcomingbias-pages[recaptcha,redis]; extra == 'production'
Provides-Extra: recaptcha
Requires-Dist: google-cloud-recaptcha-enterprise; extra == 'recaptcha'
Provides-Extra: redis
Requires-Dist: hiredis; extra == 'redis'
Requires-Dist: redis>=4; extra == 'redis'
Provides-Extra: test
Requires-Dist: pytest; extra == 'test'
Requires-Dist: pytest-django; extra == 'test'
Requires-Dist: python-dotenv; extra == 'test'
